fastapi_extended_route/__init__.py
fastapi_extended_route-0.0.0.dist-info/METADATA
fastapi_extended_route-0.0.0.dist-info/WHEEL
fastapi_extended_route-0.0.0.dist-info/top_level.txt
fastapi_extended_route-0.0.0.dist-info/RECORD
