Metadata-Version: 2.1
Name: fastapi-extended-route
Version: 0.0.0
Summary: A small utility for FastAPI Router.
Home-page: https://github.com/aminalaee/fastapi_extended_route
Author: Amin Alaee
Author-email: mohammadamin.alaee@gmail.com
License: BSD
Classifier: Development Status :: 3 - Alpha
Classifier: Environment :: Web Environment
Classifier: Intended Audience :: Developers
Classifier: License :: OSI Approved :: BSD License
Classifier: Operating System :: OS Independent
Classifier: Topic :: Internet :: WWW/HTTP
Classifier: Programming Language :: Python :: 3
Classifier: Programming Language :: Python :: 3.7
Classifier: Programming Language :: Python :: 3.8
Classifier: Programming Language :: Python :: 3.9
Classifier: Programming Language :: Python :: 3.10
Classifier: Programming Language :: Python :: 3.11
Requires-Python: >=3.7
Requires-Dist: starlette
